detect_package/__init__.py
detect_package/detect.py
detect_package/frozen_dir.py
detect_package/model-encrypted
detect_package/road-encrypted
road_detect-0.0.1.dist-info/LICENSE
road_detect-0.0.1.dist-info/METADATA
road_detect-0.0.1.dist-info/WHEEL
road_detect-0.0.1.dist-info/top_level.txt
road_detect-0.0.1.dist-info/RECORD
