Metadata-Version: 2.1
Name: road-detect
Version: 0.0.1
Summary: A demo for road detect.
Home-page: UNKNOWN
Author: zhang1992wen1023
Author-email: 591603256@qq.com
License: UNKNOWN
Keywords: detect
Platform: UNKNOWN
Classifier: Programming Language :: Python :: 3
Classifier: License :: OSI Approved :: MIT License
Classifier: Operating System :: OS Independent
License-File: LICENSE
Requires-Dist: Crypto (==3.11.0)
Requires-Dist: flask (==1.1.2)
Requires-Dist: numpy (==1.18.5)
Requires-Dist: pandas (==1.0.5)
Requires-Dist: xgboost (==1.4.2)
Requires-Dist: shap (==0.40.0)
